django_rszio-1.1.0.dist-info/DESCRIPTION.rst
django_rszio-1.1.0.dist-info/METADATA
django_rszio-1.1.0.dist-info/RECORD
django_rszio-1.1.0.dist-info/WHEEL
django_rszio-1.1.0.dist-info/metadata.json
django_rszio-1.1.0.dist-info/top_level.txt
django_rszio-1.1.0.dist-info/zip-safe
rszio/__init__.py
rszio/admin.py
rszio/apps.py
rszio/models.py
rszio/tests.py
rszio/urls.py
rszio/views.py
rszio/migrations/__init__.py
rszio/templatetags/__init__.py
rszio/templatetags/rszio.py
