Metadata-Version: 2.0
Name: django-rszio
Version: 1.1.0
Summary: Django wrapper for RSZ.IO
Home-page: https://github.com/g3rd/django-rszio
Author: Chad Shryock
Author-email: chad@keystone.works
License: MIT
Keywords: django resize image
Platform: UNKNOWN
Classifier: Framework :: Django
Classifier: License :: OSI Approved :: MIT License
Classifier: Operating System :: OS Independent
Classifier: Programming Language :: Python :: 3.4
Classifier: Programming Language :: Python :: 3.5
Classifier: Programming Language :: Python :: 3.6
Requires-Dist: django (>=1.10)
Requires-Dist: requests (>=2.14.2)
